README.md
setup.py
DingDingBot/DDBOT.py
DingDingBot/__init__.py
DingDingBot.egg-info/PKG-INFO
DingDingBot.egg-info/SOURCES.txt
DingDingBot.egg-info/dependency_links.txt
DingDingBot.egg-info/top_level.txt