Metadata-Version: 1.2
Name: DingDingBot
Version: 2.0
Summary: this is a dingdingbot packages
Home-page: UNKNOWN
Author: Jruing
Author-email: 1099301992@qq.com
License: UNKNOWN
Platform: UNKNOWN
Requires: requests
Requires-Python: >=3
